stepfunctions/__init__.py
stepfunctions/exceptions.py
stepfunctions/inputs/__init__.py
stepfunctions/inputs/placeholders.py
stepfunctions/inputs/utils.py
stepfunctions/steps/__init__.py
stepfunctions/steps/choice_rule.py
stepfunctions/steps/compute.py
stepfunctions/steps/fields.py
stepfunctions/steps/integration_resources.py
stepfunctions/steps/service.py
stepfunctions/steps/states.py
stepfunctions/steps/utils.py
stepfunctions/template/__init__.py
stepfunctions/template/utils.py
stepfunctions/template/pipeline/__init__.py
stepfunctions/template/pipeline/common.py
stepfunctions/template/pipeline/inference.py
stepfunctions/template/pipeline/train.py
stepfunctions/workflow/__init__.py
stepfunctions/workflow/cloudformation.py
stepfunctions/workflow/stepfunctions.py
stepfunctions/workflow/utils.py
stepfunctions/workflow/widgets/__init__.py
stepfunctions/workflow/widgets/events_table.py
stepfunctions/workflow/widgets/executions_table.py
stepfunctions/workflow/widgets/graph.py
stepfunctions/workflow/widgets/utils.py
stepfunctions/workflow/widgets/workflows_table.py
stepfunctions_without_sagemaker-3.0.0.dist-info/LICENSE
stepfunctions_without_sagemaker-3.0.0.dist-info/METADATA
stepfunctions_without_sagemaker-3.0.0.dist-info/WHEEL
stepfunctions_without_sagemaker-3.0.0.dist-info/top_level.txt
stepfunctions_without_sagemaker-3.0.0.dist-info/RECORD
