Metadata-Version: 2.1
Name: stepfunctions-without-sagemaker
Version: 3.0.0
Summary: Open source library for developing data science workflows on AWS Step Functions.
Home-page: https://github.com/nsbno/aws-step-functions-data-science-sdk-python
Author: Amazon Web Services
License: Apache License 2.0
Keywords: ML Amazon AWS AI Tensorflow MXNet
Classifier: Intended Audience :: Developers
Classifier: Natural Language :: English
Classifier: License :: OSI Approved :: Apache Software License
Classifier: Programming Language :: Python
Classifier: Programming Language :: Python :: 3.6
License-File: LICENSE
Requires-Dist: boto3 >=1.14.38
Requires-Dist: pyyaml
Provides-Extra: sagemaker
Requires-Dist: sagemaker >=2.1.0 ; extra == 'sagemaker'
Provides-Extra: test
Requires-Dist: tox >=3.13.1 ; extra == 'test'
Requires-Dist: pytest >=4.4.1 ; extra == 'test'
Requires-Dist: stopit ==1.1.2 ; extra == 'test'
Requires-Dist: tensorflow >=1.3.0 ; extra == 'test'
Requires-Dist: contextlib2 ==0.5.5 ; extra == 'test'
Requires-Dist: IPython ; extra == 'test'
